sig_saturate/__init__.py
sig_saturate/app.py
sig_saturate/run.py
sig_saturate-0.1.0.dist-info/LICENSE
sig_saturate-0.1.0.dist-info/METADATA
sig_saturate-0.1.0.dist-info/WHEEL
sig_saturate-0.1.0.dist-info/entry_points.txt
sig_saturate-0.1.0.dist-info/top_level.txt
sig_saturate-0.1.0.dist-info/RECORD
