Metadata-Version: 2.1
Name: sig-saturate
Version: 0.1.0
Summary: Second-Order Lag System with Saturation
Home-page: https://github.com/bokey007/sig_saturate
Author: Sudhir Arvind Deshmukh
License-File: LICENSE
Requires-Dist: numpy
Requires-Dist: matplotlib
Requires-Dist: streamlit
